[
  {
    "name": "theme_info",
    "theme_name": "Theme Sales",
    "theme_version": "1.0.0",
    "theme_author": "WebSilk",
    "theme_documentation_url": "https://api.media.websilk.net/doc/73452/content",
    "theme_support_email": "support-developers@websilk.net"
  },
  {
    "name": "Header",
    "settings": [
      {
        "type": "image_picker",
        "id": "header_logo",
        "label": "Header Logo",
        "info": "Your logo for the header"
      },
      {
        "type": "color",
        "id": "header_background_color",
        "label": "Header Background Color",
        "default": "#181818"
      },
      {
        "type": "range",
        "id": "header_background_opacity",
        "label": "Header Background Opacity",
        "min": 0,
        "max": 100,
        "step": 1,
        "default": 95,
        "unit": "%"
      },
      {
        "type": "range",
        "id": "header_logo_size",
        "label": "Scale Logo",
        "min": 50,
        "max": 200,
        "step": 1,
        "default": 100,
        "unit": "px"
      }
    ]
  }
]
